khmerocr/__init__.py
khmerocr/preprocessing.py
khmerocr-1.0.0.0.dist-info/METADATA
khmerocr-1.0.0.0.dist-info/WHEEL
khmerocr-1.0.0.0.dist-info/top_level.txt
khmerocr-1.0.0.0.dist-info/RECORD
